molecule_qemu/__init__.py
molecule_qemu/driver.json
molecule_qemu/driver.py
molecule_qemu/cookiecutter/cookiecutter.json
molecule_qemu/cookiecutter/{{cookiecutter.molecule_directory}}/{{cookiecutter.scenario_name}}/collections.yml
molecule_qemu/cookiecutter/{{cookiecutter.molecule_directory}}/{{cookiecutter.scenario_name}}/converge.yml
molecule_qemu/cookiecutter/{{cookiecutter.molecule_directory}}/{{cookiecutter.scenario_name}}/prepare.yml
molecule_qemu/cookiecutter/{{cookiecutter.molecule_directory}}/{{cookiecutter.scenario_name}}/requirements.yml
molecule_qemu/playbooks/cleanup.yml
molecule_qemu/playbooks/create.yml
molecule_qemu/playbooks/destroy.yml
molecule_qemu/playbooks/edk2-aarch64.fd
molecule_qemu/playbooks/edk2-x86_64.fd
molecule_qemu/playbooks/side_effect.yml
molecule_qemu/playbooks/templates/meta-data.j2
molecule_qemu/playbooks/templates/user-data.j2
molecule_qemu-0.5.12.dist-info/LICENSE
molecule_qemu-0.5.12.dist-info/METADATA
molecule_qemu-0.5.12.dist-info/WHEEL
molecule_qemu-0.5.12.dist-info/entry_points.txt
molecule_qemu-0.5.12.dist-info/top_level.txt
molecule_qemu-0.5.12.dist-info/RECORD
