Metadata-Version: 2.1
Name: molecule-qemu
Version: 0.5.12
Summary: Molecule QEMU
Author-email: Andrey Gubarev <andrey@andreygubarev.com>
License: MIT
Project-URL: Homepage, https://github.com/andreygubarev/molecule-qemu/
License-File: LICENSE
Requires-Dist: molecule>=5.0
